NEMO_hydra/__init__.py
NEMO_hydra/apps.py
NEMO_hydra/customizations.py
NEMO_hydra/properties_schemas.py
NEMO_hydra/templates/NEMO_hydra/customizations/customizations_hydra.html
NEMO_hydra/tests/__init__.py
NEMO_hydra/tests/test_hydra.py
NEMO_hydra/tests/test_settings.py
nemo_hydra-0.1.2.dist-info/licenses/LICENSE
nemo_hydra-0.1.2.dist-info/METADATA
nemo_hydra-0.1.2.dist-info/WHEEL
nemo_hydra-0.1.2.dist-info/top_level.txt
nemo_hydra-0.1.2.dist-info/RECORD
