Metadata-Version: 2.4
Name: NEMO-hydra
Version: 0.1.2
Summary: Plugin to facilitate NEMO integration within Hydra
Author-email: Atlantis Labs LLC <atlantis@atlantislabs.io>
License: MIT License
Project-URL: Homepage, https://gitlab.com/nemo-community/atlantis-labs/nemo-hydra
Project-URL: Changelog, https://gitlab.com/nemo-community/atlantis-labs/nemo-hydra/-/releases
Project-URL: Issues, https://gitlab.com/nemo-community/atlantis-labs/nemo-hydra/-/issues
Project-URL: CI, https://gitlab.com/nemo-community/atlantis-labs/nemo-hydra/-/pipelines
Keywords: NEMO
Classifier: Development Status :: 5 - Production/Stable
Classifier: Intended Audience :: Developers
Classifier: License :: OSI Approved :: MIT License
Classifier: Framework :: Django :: 4.2
Classifier: Programming Language :: Python :: 3.9
Classifier: Programming Language :: Python :: 3.10
Classifier: Programming Language :: Python :: 3.11
Classifier: Programming Language :: Python :: 3.12
Classifier: Programming Language :: Python :: 3.13
Requires-Python: >=3.9
License-File: LICENSE
Requires-Dist: django
Provides-Extra: nemo-ce
Requires-Dist: NEMO-CE>=7.2.0; extra == "nemo-ce"
Provides-Extra: nemo
Requires-Dist: NEMO>=7.2.0; extra == "nemo"
Provides-Extra: dev-tools
Requires-Dist: pre-commit; extra == "dev-tools"
Requires-Dist: djlint; extra == "dev-tools"
Requires-Dist: black; extra == "dev-tools"
Dynamic: license-file
